noteagator/__init__.py
noteagator/__main__.py
noteagator/config.py
noteagator/fsutils.py
noteagator/main.py
noteagator/note.py
noteagator/print_utils.py
noteagator/commands/dir.py
noteagator/commands/notes.py
noteagator-0.1.3.dist-info/licenses/LICENSE
noteagator-0.1.3.dist-info/METADATA
noteagator-0.1.3.dist-info/WHEEL
noteagator-0.1.3.dist-info/entry_points.txt
noteagator-0.1.3.dist-info/top_level.txt
noteagator-0.1.3.dist-info/RECORD
