Metadata-Version: 2.4
Name: noteagator
Version: 0.1.3
Summary: Notebook Navigator a keyboard first note tool
Author: William Lindsey
License: MIT License
Project-URL: Homepage, https://github.com/willlindsey05/noteagator
Project-URL: Issues, https://github.com/willlindsey05/noteagator/issues
Keywords: cli,notes,markdown,productivity
Classifier: Programming Language :: Python :: 3
Classifier: License :: OSI Approved :: MIT License
Classifier: Operating System :: OS Independent
Requires-Python: >=3.10
License-File: LICENSE
Requires-Dist: click<9.0,>=8.2
Requires-Dist: pyyaml<7,>=6
Requires-Dist: rich<15,>=14
Requires-Dist: pyperclip<2.0,>=1.9
Provides-Extra: test
Requires-Dist: pytest<9,>=8; extra == "test"
Dynamic: license-file
